{"song_id":21096,"song_name":"You'll Always Be Loved By Me","artist_id":297731,"display_artist":"Brooks & Dunn","spotify_id":"1migZXJuB0tB2pFucCtEm5","lyrics":"I know forever is a long long time\nFor a girl to put her heart on the line\nTrust is a tight rope we all have to walk\nBaby don't be afraid I won't let you fall\nWith a little faith mountains move\nYou and me we can't lose\n\nYou can count on the sun to rise\nAnd stars to come out at night\nAs long as there's air to breathe\nYou'll always be loved by me\n\nLove comes so many times goes\nSo much out there we'll never know\nCall it fate call it destiny\nBut I think we were meant to be\nThis old world it spins so fast\nSo many times they just don't last\n\nYou can count on the sun to rise\nAnd stars to come out at night\nAs long as there's air to breathe\nYou'll always be loved by me\n\nYou can count on the sun to rise\nAnd stars to come out at night\nAs long as there's air to breathe\nYou'll always be loved by me\n\nYou'll always be loved by me"}