{"song_id":21635,"song_name":"Rainy Dayz","artist_id":309851,"display_artist":"Mary J. Blige Featuring Ja Rule","spotify_id":"1F1XjwRzMh8KT2BvH6ISkG","lyrics":"Hey, yeah\nRule baby, yeah\nMary J. Blige\nMurder Inc.\nSmile\n\nIt's just those rainy days\nSpend a lifetime, tryin' to wash away\nUntil the sun comes out and shines again\nSmile for me, smile for me\n\nAll of those rainy days\nSpend your lifetime, tryin' to wash away\nUntil the sun shines and I see your face\nSmile at me, smile at me\n\nWe were always livin' so crazy and sexy and cool\nAnd we began to love it (began to love it)\nWatchin' all of the heartache and pain of the world\nAnd thinkin' nothin' of it (thinkin' nothin' of it)\nAnd baby, I got a love for you\nAnd I know that you got me, baby\nBut every time the sun shines bright\nIt gets so cloudy\n\nIt's just those rainy days\nSpend a lifetime tryin' to wash away\nUntil the sun comes out and shines again\nSmile for me, smile for me\n\nAll of those rainy days\nSpend your lifetime tryin' to wash away\nUntil the sun shines and I see your face\nSmile at me, smile at me\n\nCause nobody loves the rain\n\nCan't stand it\nBut it always seems to fall\n\nBaby, handle it\nBaby, didn't we tell ya before\nAbout chasin' those waterfalls\nChasin' waterfalls\nYeah\n\nCause nobody loves the rain\n\nCan't stand it\nBut it always seems to fall\n\nBaby, handle it\nBaby, what did we tell ya before\nAbout chasin' those waterfalls\n\nYeah\n\nYeah, baby\nSometimes the Rule don't mind the rain\nIt kinda feels like I'm drownin' in the Lord's pain\nUntil the sun comes out and shines again\nSmile, and give me a reason to keep on believin'\nThat everything ain't misleadin'\nAnd I kiss the clouds on them rainy days\nAnd smile for you, when the skies are gray\nBabe, 'cause I'm a tear drop away from cryin'\nAnd a few shots away from dyin'\nDear Lord, would you shower my pain\nLet it rain, let it rain on me\nWhile I cherish the air I breathe\nI'm an angel, that can't soar, can't fly\nAnd I mastered it, Lord knows why\n\nIt's just those rainy days\nSpend a lifetime tryin' to wash away\nUntil the sun comes out and shines again\nSmile for me, smile for me\n\nAll of those rainy days\nSpend your lifetime tryin' to wash away\nUntil the sun shines and I see your face\nSmile at me, smile at me\n\nI feel like an angel\nWith my broken wings\nSo I can soar again\nLord, let me in\nBaby, through all the passion, the pain, and the hurt\nI feel like I'm fallin', yeah\n\nMakin' clothes for all of those\nThat spread the love\nAnd for those who can't take it\nStand up\nBaby, we gonna make it\nIn the words of Marvin Gaye\nWar is not the answer\n\nNobody loves the rain\n\nCan't stand it\nBut it always seems to fall\n\nBaby, handle it\nBaby, didn't we tell ya before\nAbout chasin' those waterfalls\nChasin' waterfalls\n\nYeah\n\nNobody loves the rain\n\nCan't stand it\nBut it always seems to fall\n\nBaby, handle it\nBaby, what did we tell ya before\nAbout chasin' those waterfalls\n\nYeah\n\nIt's just those rainy days\nSpend a lifetime tryin' to wash away\nUntil the sun come out and shines again\nSmile for me, smile for me\n\nAll of those rainy days\nSpend your lifetime tryin' to wash away\nUntil the sun shines and I see your face\nSmile at me, smile at me\n\nSmile, smile, smile, smile\nSmile, smile, smile, smile, smile\nTill the sun shines\nJust smile for me\nJust smile for me, just smile at me\nKnow in your heart, that we are free\nFree to believe, whatever we feel\nSo feel somethin' real, baby\nHey"}