{"rank":"85","song_id":"17980","song_name":"Spending My Time","artist_id":"369191","display_artist":"Roxette","spotify_id":"11cPZ4QLCxU0IAREiOBOZI","lyrics":"What's the time, seems it's already morning\nI see the sky, it's so beautiful and blue\nThe TV's on but the only thing showing is a picture of you\n\nOh I get up and make myself some coffee\nI try to read a bit, but the story is too thin\nI thank the Lord above that you're not here to see me\nIn this shape I'm in\n\nSpending my time\nWatching the days go by\nFeeling so small, I stare at the wall\nHoping that you think of me too\nI'm spending my time\n\nI try to call but I don't know what to tell you\nI leave a kiss on your answering machine\nOh help me please is there someone who can make me\nWake up from this dream?\n\nSpending my time\nWatching the days go by\nFeeling so small, I stare at the wall\nHoping that you are missing me too\n\nI'm spending my time\nWatching the sun go down\nI fall asleep to the sound\nOf \"tears of a clown\"\nA prayer gone blind\nI'm spending my time\n\nMy friends keep telling me hey life will go on\nTime will make sure I'll get over you ooh\nThis silly game of love - you play, you win only to lose\n\nI'm spending my time\nWatching the days go by\nFeeling so small, I stare at the wall\nHoping that you think of me too\n\nI'm spending my time\nWatching the sun go down\nI fall asleep to the sound\nOf \"tears of a clown\"\nA prayer gone blind\nI'm spending my time\n\nI'm spending my time..."}