{"rank":"98","song_id":"18211","song_name":"Honey Love","artist_id":"277270","display_artist":"R. Kelly","spotify_id":"11HfPVqgorTbvDCN9JPZcA","lyrics":"Uh, yeah, come inside\nNow turn the lights down\nDon't be scared, touch me\nI know what you want and all\nTonight is your night\nFor the rest of your life\nSo just lay back and relax and listen\n\nThere's something in your eyes, baby\nIt's telling me you want me, baby\nTonight is your night\nSee, you don't have to ask for nothing\nI?ll give you everything you need\nSo girl, don't be shy, oh...just\n\n(Baby, come inside) Oh, turn down the lights\n'Cause there is something that I want from you right now, ooh\n\n(Give me that honey love) Give me that honey love\n(Give me that honey love) I gotta have your loving, baby, oh...\n(Give me that honey love) Oh...give me that sweet, sweet love\n(Give me that honey love) Oh...yeah\n\nLet's go to the mall, baby\nI'll pick you up around the way\nDon?t you worry ?bout a thing, ooh...ooh...\n'Cause I?ve got all the answers, girl\nTo the questions in your head\nAnd I'm gonna be right there for you, baby, hey\n\n(Baby, come inside) Girl, why don't you turn down the lights\n'Cause there is something that I want from you right now, hey\n\n(Give me that honey love) Give it to me\n(Give me that honey love) See, I gotta have your honey love, baby, slow\n(Give me that honey love) Give me that sweet, sweet love, hey\n(Give me that honey love) Ooh, so\n\n(Baby, come inside) Woo, turn down the lights\n'Cause there is something that I want from you right now\n\n(Give me that honey love) Whoa...oh...whoa...oh...oh...whoa...\n(Give me that honey love) Give me that honey love right now, baby\n(Give me that honey love)\n\nJust like a lollipop\nYou're so sweet, yeah\nAnd your body's like a lemon drop\nSure taste good to me\nSo let's lay down\nAnd get close till we become one\nAnd I promise you, baby\nOoh, we're gonna have fun, alright\n\n(Give me that honey love) Give me that honey love right\n(Give me that honey love) I want it right now, hey\n(Give me that honey love) I...I...I\n(Give me that honey love) Right now give me that honey love, listen\n\n(Give me that honey love) There ain't nothing I won't do for you, woo, woo, woo, woo, woo\n(Give me that honey love) I'm here to satisfy you, baby\nAnd it's good to know that you are my lady, oh\n(Give me that honey love) Oh, I gotta have your honey love\n(Give me that honey love) Right now, right now, right now, right now, right now\n\n(Give me that honey love) Whoa...oh...oh...oh...oh...oh...oh...oh..."}