{"rank":"44","song_id":"18855","song_name":"I m Ready","artist_id":"376920","display_artist":"Tevin Campbell","spotify_id":"3vQQ6sNWRLfWXrnL04bIe0","lyrics":"VERSE 1:\n\nBaby, it was uncool to love me\nThen leave me standing here now\nWithout a goodbye\nAnd maybe I am the fool you call me\n'Cause I'll be here standing waiting\nTo hear you say to me\n\nCHORUS:\n\nI'm ready (You know I'm ready)\nTo love you (To love you)\nForever (Forever)\nAnd ever, baby\nCome and love me forever more\n\nREPEAT CHORUS\n\nVERSE 2:\n\nSometimes, when I'm alone I feel sad\n'Cause I know you'll meet me once again\nAnd take my pride\nAnd maybe I am the fool you call me\n'Cause I'll be here standing waiting\nTo hear you say to me\n\nCHORUS\n\nAnd once again I'll be right here\nWaiting to share your love\nAnd oh this for once\nWe'll forever be in love\n\n"}