{"rank":"28","song_id":"19752","song_name":"I Finally Found Someone (From \"The Mirror Has Two Faces\")","artist_id":"280667","display_artist":"Barbra Streisand & Bryan Adams","spotify_id":"2WthqeuPLwn0CHwCMrlt6L","lyrics":"Mmm, yeah\nMmm\nI finally found someone\nWho knocks me off my feet\nI finally found the one\nThat makes me feel complete\nIt started over coffee\nWe started out as friends\nIt's funny how from simple things\nThe best things begin\nThis time is different\n(La la la la)\nIt's all because of you\n(La la la la)\nIt's better than it's ever been\n'Cause we can talk it through\nMy favorite line was\n\"Can I call you sometime?\"\nIt's all you had to say\nTo take my breath away\nThis is it\nOh, I finally found someone\nSomeone to share my life\nI finally found the one to be with every night\n'Cause whatever I do\nIt's just got to be you\nMy life has just begun\nI finally found someone\nHmm, someone\nI finally found someone, ooh\nDid I keep you waiting?\nI didn't mind\nI apologize\nBaby, that's fine\nI would wait forever just to know you were mine\nYa know I love your hair\nAre you sure it looks right?\nI love what you wear\nIsn't it too tight?\nBut you're exceptional\nI can't wait for the rest of my life\nThis is it\nOh, I finally found someone\nSomeone to share my life\nI finally found the one to be with every night\n'Cause whatever I do\nIt's just got to be you, oh yeah\nMy life has just begun\nI finally found someone\nAnd whatever I do\nIt's just got to be you\nOoh, my life has just begun\nI finally found someone"}