{"rank":"71","song_id":"19962","song_name":"Rhythm Of Love","artist_id":"276001","display_artist":"DJ Company","spotify_id":"1YQavetDKlRA3zUpi4Igty","lyrics":"And if you feel the need to make love till the end of night\nAnd if you wanna make love till you see morning light\nIt's the rhythm of my love, oh yeah, the rhythm of love\nIt's the rhythm of my love, oh yeah, the rhythm of love\n\nOoh we explode on emotional overload\nWhen I come down you get high\nTogether we could fly\nYo, when it gets real rough\nYou still can't get enough\nNo, come at me to do\nThe things you want me to\n\nFull acceleration to the point of elevation\nWe were tied above to the rhythm of a love\nNobody can stop us and nobody can drop us\nYo, 1 2 3 4 we got the rhythm!\n\nYeah check it out\nHey can't you feel it\nYou can't take my beat and steal it\nIssue me, the one and only\nBelieve me I'm no phony\nYo when I come down\nYour mind stop spinning round\nYou and your soul under my control\n\nFull acceleration to the point of elevation\nWe were tied above to the rhythm of a love\nNobody can stop us and nobody can drop us\nYo, 1 2 3 4 we got the rhythm!\n\nWe got the rhythm (3x)\nWe got got the rhythm\nWe got the rhythm\nWe got got the rhythm\n\nYeah yeah yeah yeah\nOoh yeah hea\nI got the Rythm\n\nAnd if you feel the need to make love till the end of night\nAnd if You wanna make love till you see morning light\nIt's the rhythm of my love, the rhythm, oh yeah, the rhythm\nThe rhythm of love\nIt's the rhythm of my love, the rhythm, oh yeah, the rhythm\nThe rhythm of love"}