{"rank":"42","song_id":"20355","song_name":"Ava Adore","artist_id":"279618","display_artist":"The Smashing Pumpkins","spotify_id":"4OFQXYAbpzYsJ30gXdlZHT","lyrics":"It's you that I adore\nYou'll always be my whore\nYou'll be a mother to my child\nAnd a child to my heart\n\nWe must never be apart\nWe must never be apart\n\nLovely girl, you're the beauty in my world\nWithout you, there aren't reasons left to find\n\nAnd you'll pull your crooked teeth\nYou'll be perfect just like me\nYou'll be a lover in my bed\nAnd a gun to my head\n\nWe must never be apart\nWe must never be apart\n\nLovely girl, you're the murder in my world\nDressing coffins for the souls I've left to die\nDrinking mercury to the mystery\nOf all that you should ever leave behind\nIn time\n\nIn you I see dirty\nIn you I count stars\nIn you I feel so pretty\nIn you I taste God\nIn you I feel so hungry\nIn you I crash cars\n\nWe must never be apart\n\nDrinking mercury to the mystery\nOf all that you should ever seek to find\nLovely girl, you're the murder in my world\nDressing coffins for the souls I've left behind\nIn time\n\nWe must never be apart\n\nAnd you'll always be my whore\n'Cause you're the one that I adore\nAnd you'll pull your crooked teeth\nYou'll be perfect just like me\n\nIn you I feel so dirty\nIn you I crash cars\nIn you I feel so pretty\nIn you I taste God\n\nWe must never be apart"}