{"rank":"67","song_id":"20383","song_name":"What U See Is What U Get","artist_id":"431562","display_artist":"Xzibit","spotify_id":"2bP1dyodgBEN94xWvjk7lb","lyrics":"Forget your sweetest dreams\n\nForget it 'cause it breaks\n\nYou ask yourself what went wrong\n\nWhen we decided to jump off\n\nForget what you know\n\nForget what you saw\n\nAll those flashes drove us blind\n\nYou can't get them off your mind\n\nWe let them taste what they'll never have\n\nForget the place\n\nForget the time\n\nWhat you get is what you see\n\nI'm trying to say I don't care\n\nWhat's your perversion?\n\nForget the sweetest days\n\nForget it 'cause it breaks\n\nHow long will you be a star?\n\nWaiting for the show to start\n\nWhat you get is what you see\n\nForget the place\n\nForget the time\n\nWhat you get is what you see\n\nI'm trying to say I don't care\n\nWhat's your perversion"}