{"rank":"72","song_id":"20814","song_name":"I m Already Taken","artist_id":"280670","display_artist":"Steve Wariner","spotify_id":"6SeIgkwEboWc9m11n36WWE","lyrics":"My little third grade hand wrote I love you\nOn a note of yellow paper\nAnd sent it to the front of the row to a little blonde-haired girl\nThe blonde-haired girl just opened it and read it to herself\nI was so embarrassed when she turned around and said\n\nI'm already taken\nYou spoke up too late\nI love somebody else\nSo you'll just have to wait\n\nThe years flew by so quickly\nAnd there we were in junior high\nI realized that I still loved her so\nSo I called her up and told her exactly how I felt\nThen she said there's something that you really ought to know\n\nI'm already taken\nYou spoke up too late\nI love somebody else\nSo you'll just have to wait\n\nSo wait I did and never changed my love for that little blonde-haired girl\nWhos' now the mother of our little blonde-haired boy\nWho's to our hearts so close\nI hate to think how fast he's growing up\nLast night I overheard them as she tucked him into bed\nHe said, Mommy will you marry me\nAnd this is what she said\n\nI'm already taken\nYou spoke up too late\nI love your daddy son\nSo you'll just have to wait\n\nI'm already taken\nYou spoke up too late\nI love your daddy son\nSo you'll just have to wait"}