{"rank":"78","song_id":"20956","song_name":"No Leaf Clover","artist_id":"310639","display_artist":"Metallica","spotify_id":null,"lyrics":"And it feels right this time,\r\nOn his crash course with the big time\r\nPay no mind to the distant thunder,\r\nNew day fills his head with wonder, boy\r\n\r\nSays it feels right this time\r\nTurned it 'round and found the right line\r\nGood day to be alive, Sir\r\nGood day to be alive he says.\r\n\r\nThen it comes to be\r\nthat the soothing light\r\nat the end of your tunnel\r\nwas just a freight train coming your way, yeah.\r\nwas just a freight train coming your way, yeah.\r\n\r\nDon't it feel right like this?\r\nAll the pieces fall to his wish\r\nSucker for that quick reward, boy\r\nSucker for that quick reward they say.\r\n\r\nThen it comes to be\r\nthat the soothing light\r\nat the end of your tunnel\r\nwas just a freight train coming your way, yeah.\r\nwas just a freight train coming your way, yeah.\r\nIt's coming your way.\r\nIt's coming your way, yeah.\r\nHere comes!\r\n\r\nYeah, Then it comes to be\r\nthat the soothing light\r\nat the end of your tunnel\r\nwas just a freight train coming your way, yeah.\r\n\r\nThen it comes to be, Yeah.\r\nThen it comes to be, Yeah.\r\nThen it comes to be, Yeah.\r\nThen it comes to be, Yeah.\r\nThen it comes to be, Yeah.\r\nThen it comes to be, Yeah.\r\nThen it comes to be, Yeah.\r\nThen it comes to be, Yeah."}