{"rank":"67","song_id":"21308","song_name":"Drive","artist_id":"303773","display_artist":"Incubus","spotify_id":"7nnWIPM5hwE3DaUBkvOIpy","lyrics":"Sometimes, I feel the fear of uncertainty stinging clear\nAnd I can't help but ask myself\nHow much I'll let the fear take the wheel and steer\n\nIt's driven me before\nAnd it seems to have a vague, haunting mass appeal\nBut lately I'm beginning to find that I\nShould be the one behind the wheel\n\nWhatever tomorrow brings I'll be there\nWith open arms and open eyes, yeah\nWhatever tomorrow brings I'll be there\nI'll be there\n\nSo if I decide to waiver my chance\nTo be one of the hive\nWill I choose water over wine\nAnd hold my own and drive?\n\nIt's driven me before\nAnd it seems to be the way\nThat everyone else gets around\nBut lately I'm beginning to find that\nWhen I drive myself my light is found\n\nWhatever tomorrow brings I'll be there\nWith open arms and open eyes, yeah\nWhatever tomorrow brings I'll be there\nI'll be there\n\nWould you choose water over wine\nHold the wheel and drive?\n\nWhatever tomorrow brings I'll be there\nWith open arms and open eyes\nWhatever tomorrow brings I'll be there\nI'll be there\n\nTomorrow\nTomorrow"}