{"rank":"51","song_id":"21802","song_name":"You Know You're Right","artist_id":"312336","display_artist":"Nirvana","spotify_id":"6oEVXNUt5x4cIMGYrKiB4w","lyrics":"I will never bother you\r\nI will never promise to\r\nI will never follow you\r\nI will never bother you\r\n\r\nNever speak a word again\r\nI will crawl away for good\r\n\r\nI will move away from here\r\nYou wont be afraid of fear\r\nNo thought was put in to this\r\nI always knew it would come to this\r\n\r\nThings have never been so swell\r\nI have never failed to fail\r\nPain\r\nPain\r\nPain\r\n\r\nYou know you're right\r\nYou know you're right\r\nYou know you're right\r\n\r\nI'm so warm and calm inside\r\nI no longer have to hide\r\nLet's talk about someone else\r\nStinging soon begins to melt\r\nNothing really bothers her\r\nShe just wants to love herself\r\n\r\nI will move away from here\r\nYou wont be afraid of fear\r\nNo thought was put into this\r\nI always knew to come like this\r\n\r\nThings have never been so swell\r\nI have never failed to fail\r\nPain\r\nPain\r\nPain\r\nPain\r\nPain\r\n\r\nYou know you're right\r\nYou know you're right\r\nYou know you're right\r\nYou know you're right\r\nYou know you're right\r\nYou know you're right\r\nYou know you're right\r\nYou know you're right\r\nYou know you're right\r\nYou know you're right\r\nYou know you're right\r\nYou know you're right\r\nYou know you're right\r\nYou know you're right\r\nYou know you're right\r\nYou know you're right\r\nYou know you're right\r\n\r\nPain"}