{"rank":"73","song_id":"21877","song_name":"No Letting Go","artist_id":"431150","display_artist":"Wayne Wonder","spotify_id":"1A0KS49SPUTb5HpVXOiSbZ","lyrics":"[Verse 1: Wayne Wonder ]\nGot somebody she's a beauty\nVery special really and truly\nTake good care of me like it's her duty\nWant you right by my side night and day\n\n[Hook: Wayne Wonder ]\nNo lettting go, no holding back\nBecause you are my lady\nWhen I'm with you its all a that\nGirl I, am so glad we've made it\nNo letting go No holding back\nNo holding Back no\nWhen I'm with you it's all a that\nAll a that\n\n[Verse 2: Wayne Wonder ]\nThey say good things must come to an end\nBut I'm optimistic about being your friend\nThough I made you cry by my doings\nWith Keisha and Anisha but that\nWas back then\n\n[Hook: Wayne Wonder ]\nNo lettting go, no holding back\nBecause you are my lady\nWhen I'm with you its all a that\nGirl I, am so glad we've made it\nNo letting go No holding back\nNo holding Back no\nWhen I'm with you it's all a that\nAll a that, yeah yeah\n\n[Bridge: Wayne Wonder ]\nReally appreciate you loving me\nAfter all that we've been thru\nReally appreciate you loving me\nAll times,time\n\n[Verse 1: Wayne Wonder ]\nGot somebody she's a beauty\nVery special really and truly\nTake good care of me like it's her duty\nWant you right by my side night and day\n\n\n[Hook: Wayne Wonder ]\nNo lettting go, no holding back\nBecause you are my lady\nWhen I'm with you its all a that\nGirl I, am so glad we've made it\nNo letting go No holding back\nNo holding Back no\nWhen I'm with you it's all a that\nAll a that\n\nNo lettting go, no holding back"}