{"rank":"68","song_id":"22692","song_name":"Just The Girl","artist_id":"394702","display_artist":"The Click Five","spotify_id":"1JURww012QnWAw0zZXi6Aa","lyrics":"She's cold and she's cruel\r\nbut she knows what she's doin'\r\nShe pushed me in the pool\r\nat our last school reunion\r\nShe laughs at my dreams\r\nbut I dream about her laughter\r\nStrange as it seems\r\nshe's the one I'm after\r\n\r\nCause she's bittersweet\r\nShe knocks me off of my feet\r\nAnd I can't help myself\r\nI don't want anyone else\r\nShe's a mystery\r\nShe's too much for me\r\nBut I keep coming back for more\r\nshe just the girl i'm lookin' for\r\n\r\nShe can't keep a secret\r\nfor more than an hour\r\nShe runs on 100 proof attitude power\r\nAnd the more she ignores me\r\nthe more I adore her\r\nWhat can I do?\r\nI'd do anything for her\r\n\r\nCause she's bittersweet\r\nShe knocks me off of my feet\r\nAnd I can't help myself\r\nI don't want anyone else\r\nShe's a mystery\r\nShe's too much for me\r\nBut I keep comin' back for more\r\nShe's just the girl I'm lookin' for\r\n\r\nThe way she sees it's me\r\non her caller I.D.\r\nShe won't pick up the phone\r\nShe'd rather be alone\r\nBut I can't give up just yet\r\nCause every word she's ever said\r\nis still ringin' in my head\r\nStill ringin' in my head\r\n\r\nShe's cold and she's cruel\r\nbut she knows what she's doin'\r\nKnows just what to say\r\nso my whole day is ruined\r\n\r\nCause she's bittersweet\r\nShe knocks me off of my feet\r\nAnd I can't help myself\r\nI don't want anyone else\r\nShe's a mystery\r\nShe's too much for me\r\nBut I keep comin' back for more\r\n\r\nCause she's bittersweet\r\nShe knocks me off of my feet\r\nAnd I can't help myself\r\nI don't want anyone else\r\nShe's a mystery\r\nShe's too much for me\r\nBut I keep comin' back for more\r\nOh, I keep comin' back for more\r\nShe's just the girl I'm lookin' for\r\n\r\nJust the girl I'm lookin' for\r\nI'm looking for (3x)\r\nJust the girl I'm looking for"}