{"rank":"77","song_id":"23697","song_name":"Take You Down","artist_id":"1486846","display_artist":"Chris Brown","spotify_id":"3XJpQ65m90QFmogv8MH1pG","lyrics":"Doo Doo Doo Doo Doo Doo\r\n(Damn,baby)\r\n(I want you)\r\n(Whoa)\r\n\r\nHere we are all alone in this room(Oohh)\r\nAnd girl I know where to start and what we gone do(Yeah)\r\nI'll take my time we'll be all night girl\r\nSo get ready babe I got plans for me and youu\r\n(Whoooa Ooohh)\r\n\r\n\r\nIt ain't my first time but baby girl we\r\nCan pretend (Hey)\r\nLet's bump and grind girl tonight will never end\r\n\r\nLet me take you down\r\n\r\n\r\nI really wanna take you down\r\nAnd show you what I'm about\r\nCan I take you now?\r\nYour body body (Oohhh)\r\nYour body body up and down\r\nSo don't stop girl get it\r\nQuit playin' wit it\r\nCan't wait no moreee\r\nI wanna take you down\r\nI really wanna take you down\r\nTake you down\r\n(Yeahhh,Yeahh,Yeaaahhh,Yeaaahh)\r\n\r\nPretty girl lets take it off\r\nIn this room\r\nNo time to waste\r\nGirl,you no what we came to do\r\nWe got all night to try to get it right girl\r\n(I hope you ready, hope you ready, hope you ready)\r\nI hope you ready babe,cuz here we go,you know how we doooooo\r\n(Ooooaaa)\r\n\r\nIt ain't my first time(No)but baby girl we can pretend (Hey)\r\nLet's bump and grind girl tonight will never end\r\n\r\n\r\nLet Me Take You Down\r\n\r\nI really wanna take you down\r\nAnd show you what I'm about(I'm abooouuuttt)\r\nCan I take you now?(oh yeahhh)\r\nYour body body (oooohhh)\r\nbody body up and down\r\nSo don't stop girl get it\r\nQuit playing wit it\r\nCan't wait no more(I can't wait no more)\r\nI wanna take you down\r\nI really wanna take, I really wanna take you downnn\r\n(Yeahhh)\r\n\r\nI want you\r\n\r\nFreakin (ooohh) baby\r\nLike a prooo baby\r\nAnd I bet that you\r\nI bet you (oooohh whooahh)\r\nThinkin (oohh) baby\r\nLike a pro baby\r\nSo what you wanna do\r\n\r\nI'm gonna take you down,baby nice and slow\r\nSo bring it let's goooo\r\nBabbbyyyyyyy\r\n(Babyyy)(oooo)\r\nyea, yea, babyyyyy\r\n\r\n(Come on baby, come on baby,come on baby)\r\n\r\nLet me taaakkkee you down\r\n\r\n\r\nI really wanna take you down\r\n(Lemme show you,let me do it to you,like I wanna do)\r\n(Ooooh)\r\nCan I take you now?(ooo)\r\nYa body body upppp\r\nbody body up and down (yea, yea, yea,yea)\r\nSo don't stop (oooohh)girl get it\r\nQuit playing wit it\r\nCan't wait no more (I can't wait no moreeee, oo whoaa)\r\nI wanna take you down,I really wannna take you downnnn(oooohhh)\r\n\r\nTake you down (ooooh whooa)\r\nI said I wanna take you down (yea,yeahh)\r\nLet me take you down (all the way down,all the way down)\r\nWe can do some thangs goin' all the way downnn\r\n\r\n\r\n..."}