{"rank":"78","song_id":"24517","song_name":"I Gotta Get To You","artist_id":"302752","display_artist":"George Strait","spotify_id":null,"lyrics":"I gotta get to you cause you sure been gettin' to me \nGotta find a way to get to your heart to sweep you off your feet \nI wrap you up in love, cover you with kisses so sweet \nI gotta get to you cause you sure been gettin' to me \n\nI'll win you over, over and over again \nI'm gettin closer, closer than I ever been \n\nI gotta get to you cause you sure been gettin' to me \nGotta find a way to get to your heart to sweep you off your feet \nI wrap you up in love, cover you with kisses so sweet \nI gotta get to you cause you sure been gettin' to me \n\n(instrumental) \n\nI'll keep on tryin, trying and I'll never give up \nI would be lying, If I said we were close enough \n\nI gotta get to you cause you sure been gettin' to me \nGotta find a way to get to your heart to sweep you off your feet \nI wrap you up in love, cover you with kisses so sweet \nI gotta get to you cause you sure been gettin' to me \nGotta get to you cause you sure been gettin' \nGotta get to you cause you sure been gettin' to me \n  \nby: Elvitoreo"}