{"rank":"16","song_id":"25658","song_name":"Diamonds","artist_id":"365068","display_artist":"Rihanna","spotify_id":"65YsalQBmQCzIPaay72CzQ","lyrics":"Shine bright like a diamond\nShine bright like a diamond\n\nFind light in the beautiful sea\nI choose to be happy\nYou and I, you and I\nWe're like diamonds in the sky\n\nYou're a shooting star I see\nA vision of ecstasy\nWhen you hold me, I'm alive\nWe're like diamonds in the sky\n\nI knew that we'd become one right away\nOh, right away\nAt first sight I felt the energy of sun rays\nI saw the life inside your eyes\n\nSo shine bright, tonight, you and I\nWe're beautiful like diamonds in the sky\nEye to eye, so alive\nWe're beautiful like diamonds in the sky\n\nShine bright like a diamond\nShine bright like a diamond\nShine bright like a diamond\nWe're beautiful like diamonds in the sky\n\nShine bright like a diamond\nShine bright like a diamond\nShine bright like a diamond\nWe're beautiful like diamonds in the sky\n\nPalms rise to the universe\nAs we, moonshine and molly\nFeel the warmth we'll never die\nWe're like diamonds in the sky\n\nYou're a shooting star I see\nA vision of ecstasy\nWhen you hold me, I'm alive\nWe're like diamonds in the sky\n\nAt first sight I felt the energy of sun rays\nI saw the life inside your eyes\n\nSo shine bright, tonight, you and I\nWe're beautiful like diamonds in the sky\nEye to eye, so alive\nWe're beautiful like diamonds in the sky\n\nShine bright like a diamond\nShine bright like a diamond\nShine bright like a diamond\nWe're beautiful like diamonds in the sky\n\nShine bright like a diamond\nShine bright like a diamond\nShine bright like a diamond\nWe're beautiful like diamonds in the sky\n\nShine bright like a diamond\nShine bright like a diamond\nShine bright like a diamond\nWe're beautiful like diamonds in the sky\n\nShine bright like a diamond\nShine bright like a diamond\nShine bright like a diamond\n\nSo shine bright, tonight, you and I\nWe're beautiful like diamonds in the sky\nEye to eye, so alive\nWe're beautiful like diamonds in the sky\n\nShine bright like a diamond\nShine bright like a diamond\nShine bright like a diamond\n\nShine bright like a diamond\nShine bright like a diamond\nShine bright like a diamond\n\nShine bright like a diamond"}