{"rank":"34","song_id":"26727","song_name":"679","artist_id":"6407961","display_artist":"Fetty Wap Featuring Remy Boyz","spotify_id":"5NQbUaeTEOGdD6hHcre0dZ","lyrics":"[Intro: Fetty Wap]\nYeaah baby, 17\nAy, ay, look\n\n[Verse 1: Fetty Wap]\nBaby girl, you're so damn fine though\nI'm tryna know if I could hit it from behind though\nI'm sipping on you like some fine wine though\nAnd when it's over, I press rewind though, ay\nYou talking bands, girl, I got it\nBenjamins all in my pocket\nI traded in my Trues for some Robins\nHe playing Batman, Fetty's gon rob him, ay\nI got a Glock in my 'Rari, ay, 17 shots, no 38\nI got a Glock in my 'Rari, 17 shots, no 38\n\n[Hook: Fetty Wap]\nI'm like, yeah, she's fine\nWonder when she'll be mine\nShe walk past, I press rewind\nJust to see that ass one more time\nAnd I got this sewed up\nRemy Boyz, they know us\nAll fast money, no slow bucks\nNo one can control us\nAy, yeaah baby\n\n[Verse 2: Montana Bucks]\nTell me what you see\nIs it money or it's me?\nI smoke twenty, smell the weed\nI got hunnies in my V\nThey like, Monty, can you be my baby daddy, I'm like yeah\nI got robins on my jeans, you see the wings on every pair\nAll you see is Remy Boyz, you know my niggas everywhere\nAnd if somebody got a problem, we could meet up anywhere\nNow go say something\nDon't you niggas play dumb\nYou know where we came from\nYou don't want sauce, no A1\n\n[Hook: Fetty Wap]\nI'm like, yeah, she's fine\nWonder when she'll be mine\nShe walk past, I press rewind\nJust to see that ass one more time\nAnd I got this sewed up\nRemy Boyz, they know us\nAll fast money, no slow bucks\nNo one can control us\nAy, yeaah baby\n\n[Verse 3: P-Dice]\nShe a cutie and she fine, make me wanna make her mine\nShe ain't nothing like them bimbos\nIf you like it, we can swerve, we can light and stain up here\nBlowing, pluck it out the window\nDj playing, press rewind, got her singing every time\nTake a high note for me girlfriend\nGot my city looking rude, I ain't Diddy I ain't Loon\nBut I think I need a girlfriend\nShe feeling great as I'm talking to her\nShe a Remygirl so I'm gon' pursue her\nI brought a lot of loud, lot of Remy to sip on\nThousand dollars when I get my tip on\nI'm off her, asked her if her fatty real\nShe said that's all her, got her with the happy feel\nI'm bouta spoil her, got her with the happy feel\nI'm bouta spoil her, oh my\n\n[Hook: Fetty Wap]\nI'm like, yeah, she's fine\nWonder when she'll be mine\nShe walk past, I press rewind\nJust to see that ass one more time\nAnd I got this sewed up\nRemy Boyz, they know us\nAll fast money, no slow bucks\nNo one can control us\nAy, yeaah baby\n\n[Outro: Fetty Wap]\nZoowap, Monty\nZoowap, Dicey\nYeaah baby, Remy Boyz\nYeaah, yeaah"}